{
    "META.CONFIG_COMMENT": "Apply no preprocessing",
    "META.CONFIG_NAME": "raw-high-pass-no-ica--af9f9843-fe2c-49a8-9923-0d2ef87a3ba8",
    "PREPROCESSING.DO_HIGH_PASS_FILTER": true,
    "PREPROCESSING.DO_LOW_PASS_FILTER": false,
    "PREPROCESSING.DO_MONTAGE": false,
    "PREPROCESSING.DO_REMOVE_DC": false,
    "PREPROCESSING.DO_REMOVE_EOG": false,
    "PREPROCESSING.DO_USE_ICA": false,
    "PREPROCESSING.HIGH_PASS_FILTER.FREQ": 30,
    "PREPROCESSING.LOW_PASS_FILTER.FREQ": 0.1,
    "RENDER.DO_PER_CHANNEL": true,
    "RENDER.WINDOW_OVERLAP": 1,
    "RENDER.WINDOW_WIDTH": 2
}