{
    "META.CONFIG_COMMENT": "Apply no preprocessing",
    "META.CONFIG_NAME": "raw-high-pass-ica--e6b8760b-9764-4edb-aa56-b1829174d7dd",
    "PREPROCESSING.DO_HIGH_PASS_FILTER": true,
    "PREPROCESSING.DO_LOW_PASS_FILTER": false,
    "PREPROCESSING.DO_MONTAGE": false,
    "PREPROCESSING.DO_REMOVE_DC": false,
    "PREPROCESSING.DO_REMOVE_EOG": false,
    "PREPROCESSING.DO_USE_ICA": true,
    "PREPROCESSING.HIGH_PASS_FILTER.FREQ": 50,
    "PREPROCESSING.LOW_PASS_FILTER.FREQ": 0.5,
    "RENDER.DO_PER_CHANNEL": false,
    "RENDER.WINDOW_OVERLAP": 0.4,
    "RENDER.WINDOW_WIDTH": 0.5
}